README.md
setup.py
ilogger/__init__.py
ilogger/logger.py
ilogger.egg-info/PKG-INFO
ilogger.egg-info/SOURCES.txt
ilogger.egg-info/dependency_links.txt
ilogger.egg-info/top_level.txt