Metadata-Version: 2.1
Name: ilogger
Version: 0.0.1
Summary: 超级简单的日志模块，导入即用
Home-page: https://github.com/mocobk/ilogger
Author: mocobk
Author-email: mocobk@163.com
License: UNKNOWN
Platform: UNKNOWN
Classifier: Programming Language :: Python :: 3
Classifier: License :: OSI Approved :: MIT License
Classifier: Operating System :: OS Independent
